flask_pushrod/test_all.py
flask_pushrod/normalizers.py
flask_pushrod/__init__.py
flask_pushrod/resolver.py
flask_pushrod/renderers/json.py
flask_pushrod/renderers/base.py
flask_pushrod/renderers/__init__.py
flask_pushrod/renderers/jinja2.py
Flask_Pushrod-0.3.dist-info/METADATA
Flask_Pushrod-0.3.dist-info/DESCRIPTION.rst
Flask_Pushrod-0.3.dist-info/WHEEL
Flask_Pushrod-0.3.dist-info/RECORD
Flask_Pushrod-0.3.dist-info/top_level.txt
Flask_Pushrod-0.3.dist-info/metadata.json
