Metadata-Version: 2.0
Name: Flask-Pushrod
Version: 0.3
Summary: Views for your API
Home-page: http://github.com/UYSio/flask-pushrod
Author: Juan Matthys Uys
Author-email: opyate+flaskpushrod@gmail.com
License: MIT
Platform: any
Classifier: Development Status :: 2 - Pre-Alpha
Classifier: Environment :: Web Environment
Classifier: Framework :: Flask
Classifier: Intended Audience :: Developers
Classifier: License :: OSI Approved :: MIT License
Classifier: Operating System :: OS Independent
Classifier: Programming Language :: Python
Classifier: Programming Language :: Python :: 2
Classifier: Programming Language :: Python :: 3
Classifier: Topic :: Internet :: WWW/HTTP :: Dynamic Content
Classifier: Topic :: Software Development :: Libraries :: Python Modules
Requires-Dist: Werkzeug (>=0.7)
Requires-Dist: Flask (>=0.10.1)
Requires-Dist: future
